<?xml version='1.0' encoding='UTF-8'?>
<file md5="6747d31971ac9eef45c1f2f61bd32aaa" name="4dc14f8293068eb2baf8637cf737cfb65d2e92" size="0" attrgroup="Deballer_f">
    <pose>
        <head type="SinglePoint">275,160</head>
        <neck type="SinglePoint">288,232</neck>
        <right_shoulder type="SinglePoint">349,246</right_shoulder>
        <right_elbow type="SinglePoint">398,341</right_elbow>
        <right_hand type="SinglePoint">330,389</right_hand>
        <left_shoulder type="SinglePoint">240,259</left_shoulder>
        <left_elbow type="SinglePoint">220,361</left_elbow>
        <left_hand type="SinglePoint">213,450</left_hand>
        <right_hip type="SinglePoint">341,432</right_hip>
        <left_hip type="SinglePoint">256,432</left_hip>
        <left_knee type="SinglePoint">269,582</left_knee>
        <left_ankle type="SinglePoint">303,711</left_ankle>
        <right_knee type="SinglePoint">313,576</right_knee>
        <right_ankle type="SinglePoint">269,729</right_ankle>
        <sLen_left type="StraightLine">-1,-1,-1,-1</sLen_left>
        <sLen_right type="StraightLine">335,235,346,272</sLen_right>
        <clothLen type="StraightLine">239,414,367,399</clothLen>
        <L_Sleeve type="StraightLine">null</L_Sleeve>
        <R_Sleeve type="StraightLine">342,234,343,260</R_Sleeve>
        <Lenth type="StraightLine">240,415,351,410</Lenth>
        <HSIColor1 type="StandardRect">277,323,322,349</HSIColor1>
        <HSIColor2 type="StandardRect">null</HSIColor2>
        <HSIColor3 type="StandardRect">null</HSIColor3>
    </pose>
    <attr>
        <collar>F-collar</collar>
        <uclothcnt>1</uclothcnt>
        <skirt>N</skirt>
        <uclothcategory>shirt</uclothcategory>
        <sleeve>s_no</sleeve>
        <up_length>normal</up_length>
        <texture>Single</texture>
        <button>N</button>
        <halforfull>full</halforfull>
        <bywho>deballer</bywho>
        <attrgroup>Deballer_f</attrgroup>
        <color1>15133224</color1>
        <color2>5417122</color2>
        <color3>2147286</color3>
        <color4>1988445</color4>
        <color5>1668572</color5>
        <open>open_no</open>
        <sleeveValue>0.0</sleeveValue>
        <lenthValue>36.9</lenthValue>
        <Color1>12096917</Color1>
    </attr>
</file>
