<?xml version='1.0' encoding='UTF-8'?>
<file md5="a540b843aae4ee17e493e1976091c9c8" attrgroup="Deballer_f" name="411" size="0">
    <pose>
        <head type="SinglePoint">283,73</head>
        <neck type="SinglePoint">269,163</neck>
        <right_shoulder type="SinglePoint">326,191</right_shoulder>
        <right_elbow type="SinglePoint">351,307</right_elbow>
        <right_hand type="SinglePoint">366,311</right_hand>
        <left_shoulder type="SinglePoint">193,198</left_shoulder>
        <left_elbow type="SinglePoint">185,330</left_elbow>
        <left_hand type="SinglePoint">188,422</left_hand>
        <right_hip type="SinglePoint">293,404</right_hip>
        <left_hip type="SinglePoint">222,394</left_hip>
        <left_knee type="SinglePoint">217,536</left_knee>
        <left_ankle type="SinglePoint">225,703</left_ankle>
        <right_knee type="SinglePoint">278,542</right_knee>
        <right_ankle type="SinglePoint">275,700</right_ankle>
        <L_Sleeve type="StraightLine">184,404,207,407</L_Sleeve>
        <R_Sleeve type="StraightLine">null</R_Sleeve>
        <Lenth type="StraightLine">175,531,318,532</Lenth>
        <HSIColor1 type="StandardRect">237,311,248,333</HSIColor1>
        <HSIColor2 type="StandardRect">null</HSIColor2>
        <HSIColor3 type="StandardRect">null</HSIColor3>
    </pose>
    <attr>
        <collar>V-collar</collar>
        <uclothcnt>1</uclothcnt>
        <skirt>S</skirt>
        <uclothcategory>coat</uclothcategory>
        <sleeve>s_long</sleeve>
        <up_length>mid_long</up_length>
        <texture>Single</texture>
        <button>N</button>
        <halforfull>full</halforfull>
        <bywho>deballer</bywho>
        <attrgroup>Deballer_f</attrgroup>
        <color1>14089005</color1>
        <color2>5675561</color2>
        <color3>3037412</color3>
        <color4>1872516</color4>
        <color5>1431566</color5>
        <sleeveValue>90.2</sleeveValue>
        <lenthValue>68.4</lenthValue>
        <Color1>12366773</Color1>
    </attr>
</file>
