<?xml version='1.0' encoding='UTF-8'?>
<file attrgroup="g20" md5="d3f147dd4dcb3870193dc844d209a719" name="2012RST-MWILLIAM-17fullscreen" size="0">
    <pose>
        <head type="SinglePoint">347,61</head>
        <neck type="SinglePoint">347,184</neck>
        <right_shoulder type="SinglePoint">431,198</right_shoulder>
        <right_elbow type="SinglePoint">448,363</right_elbow>
        <right_hand type="SinglePoint">452,529</right_hand>
        <left_shoulder type="SinglePoint">261,215</left_shoulder>
        <left_elbow type="SinglePoint">255,398</left_elbow>
        <left_hand type="SinglePoint">256,542</left_hand>
        <right_hip type="SinglePoint">418,470</right_hip>
        <left_hip type="SinglePoint">316,468</left_hip>
        <left_knee type="SinglePoint">319,683</left_knee>
        <left_ankle type="SinglePoint">334,910</left_ankle>
        <right_knee type="SinglePoint">394,687</right_knee>
        <right_ankle type="SinglePoint">381,914</right_ankle>
        <L_Sleeve type="StraightLine">243,418,263,421</L_Sleeve>
        <R_Sleeve type="StraightLine">463,402,414,433</R_Sleeve>
        <Lenth type="StraightLine">266,664,413,666</Lenth>
        <HSIColor1 type="StandardRect">320,399,372,419</HSIColor1>
        <HSIColor2 type="StandardRect">381,282,396,291</HSIColor2>
        <HSIColor3 type="StandardRect">null</HSIColor3>
    </pose>
    <attr>
        <collar>V-collar</collar>
        <uclothcnt>1</uclothcnt>
        <skirt>S</skirt>
        <uclothcategory>dress</uclothcategory>
        <sleeve>s_long</sleeve>
        <up_length>mid_long</up_length>
        <texture>Other</texture>
        <button>N</button>
        <halforfull>full</halforfull>
        <bywho>deballer</bywho>
        <attrgroup>g20</attrgroup>
        <color1>16723127</color1>
        <color2>3332979</color2>
        <color3>2621439</color3>
        <color4>2326011</color4>
        <color5>1436149</color5>
        <sleeveValue>60.7</sleeveValue>
        <lenthValue>66.1</lenthValue>
        <Color1>12895448</Color1>
        <Color2>5658364</Color2>
    </attr>
</file>
