<?xml version='1.0' encoding='UTF-8'?>
<file md5="e9035bfe7e81299aec52a2df538ea1f1" attrgroup="Deballer_f" name="299" size="0">
    <pose>
        <head type="SinglePoint">198,113</head>
        <neck type="SinglePoint">219,156</neck>
        <right_shoulder type="SinglePoint">258,179</right_shoulder>
        <right_elbow type="SinglePoint">272,243</right_elbow>
        <right_hand type="SinglePoint">282,312</right_hand>
        <left_shoulder type="SinglePoint">165,160</left_shoulder>
        <left_elbow type="SinglePoint">178,209</left_elbow>
        <left_hand type="SinglePoint">207,143</left_hand>
        <right_hip type="SinglePoint">233,305</right_hip>
        <left_hip type="SinglePoint">190,312</left_hip>
        <left_knee type="SinglePoint">221,402</left_knee>
        <left_ankle type="SinglePoint">250,484</left_ankle>
        <right_knee type="SinglePoint">194,392</right_knee>
        <right_ankle type="SinglePoint">185,504</right_ankle>
        <L_Sleeve type="StraightLine">156,179,178,174</L_Sleeve>
        <R_Sleeve type="StraightLine">256,204,278,193</R_Sleeve>
        <Lenth type="StraightLine">172,277,222,279</Lenth>
        <HSIColor1 type="StandardRect">201,211,218,230</HSIColor1>
        <HSIColor2 type="StandardRect">null</HSIColor2>
        <HSIColor3 type="StandardRect">null</HSIColor3>
    </pose>
    <attr>
        <collar>Round</collar>
        <uclothcnt>1</uclothcnt>
        <skirt>S</skirt>
        <uclothcategory>t-shirt</uclothcategory>
        <sleeve>s_short</sleeve>
        <up_length>normal</up_length>
        <texture>Single</texture>
        <button>N</button>
        <halforfull>full</halforfull>
        <bywho>deballer</bywho>
        <attrgroup>Deballer_f</attrgroup>
        <color1>12828346</color1>
        <color2>7310708</color2>
        <color3>2841709</color3>
        <color4>2251442</color4>
        <color5>1256230</color5>
        <sleeveValue>15.8</sleeveValue>
        <lenthValue>36.1</lenthValue>
        <Color1>14734283</Color1>
    </attr>
</file>
