<?xml version='1.0' encoding='UTF-8'?>
<file name="d57768890c7ce88b689c2340ec482c8684a9ee" size="0" md5="f2fa346921528c646815e9498867b900" attrgroup="Deballer_f">
    <pose>
        <head type="SinglePoint">316,52</head>
        <neck type="SinglePoint">299,158</neck>
        <right_shoulder type="SinglePoint">357,202</right_shoulder>
        <right_elbow type="SinglePoint">369,316</right_elbow>
        <right_hand type="SinglePoint">387,475</right_hand>
        <left_shoulder type="SinglePoint">211,193</left_shoulder>
        <left_elbow type="SinglePoint">175,334</left_elbow>
        <left_hand type="SinglePoint">175,457</left_hand>
        <right_hip type="SinglePoint">324,430</right_hip>
        <left_hip type="SinglePoint">232,433</left_hip>
        <left_knee type="SinglePoint">228,598</left_knee>
        <left_ankle type="SinglePoint">281,791</left_ankle>
        <right_knee type="SinglePoint">316,580</right_knee>
        <right_ankle type="SinglePoint">281,791</right_ankle>
        <L_Sleeve type="StraightLine">165,382,185,385</L_Sleeve>
        <R_Sleeve type="StraightLine">357,413,381,412</R_Sleeve>
        <Lenth type="StraightLine">209,431,310,425</Lenth>
        <HSIColor1 type="StandardRect">306,282,321,290</HSIColor1>
        <HSIColor2 type="StandardRect">null</HSIColor2>
        <HSIColor3 type="StandardRect">null</HSIColor3>
    </pose>
    <attr>
        <collar>V-collar</collar>
        <uclothcnt>2</uclothcnt>
        <skirt>N</skirt>
        <uclothcategory>suit</uclothcategory>
        <sleeve>s_long</sleeve>
        <up_length>normal</up_length>
        <texture>Single</texture>
        <button>B</button>
        <halforfull>full</halforfull>
        <bywho>deballer</bywho>
        <attrgroup>Deballer_f</attrgroup>
        <color1>15528846</color1>
        <color2>4801747</color2>
        <color3>2463256</color3>
        <color4>2033947</color4>
        <color5>1352265</color5>
        <sleeveValue>75.0</sleeveValue>
        <lenthValue>42.6</lenthValue>
        <Color1>3683380</Color1>
    </attr>
</file>
